LICENSE.txt
MANIFEST.in
README.rst
bootstrap.py
buildout.cfg
setup.py
xfacereclib/__init__.py
xfacereclib.paper.IET2014.egg-info/PKG-INFO
xfacereclib.paper.IET2014.egg-info/SOURCES.txt
xfacereclib.paper.IET2014.egg-info/dependency_links.txt
xfacereclib.paper.IET2014.egg-info/entry_points.txt
xfacereclib.paper.IET2014.egg-info/namespace_packages.txt
xfacereclib.paper.IET2014.egg-info/requires.txt
xfacereclib.paper.IET2014.egg-info/top_level.txt
xfacereclib/paper/__init__.py
xfacereclib/paper/IET2014/__init__.py
xfacereclib/paper/IET2014/categorical.py
xfacereclib/paper/IET2014/database_mobio.py
xfacereclib/paper/IET2014/database_scface.py
xfacereclib/paper/IET2014/dct_mobio.py
xfacereclib/paper/IET2014/dct_scface.py
xfacereclib/paper/IET2014/evaluate.py
xfacereclib/paper/IET2014/execute.py
xfacereclib/paper/IET2014/isv_mobio.py
xfacereclib/paper/IET2014/isv_scface.py
xfacereclib/paper/IET2014/plot.py
xfacereclib/paper/IET2014/utils.py