Metadata-Version: 1.1
Name: xfacereclib.paper.IET2014
Version: 1.0.0
Summary: Running the experiments as given in paper: "Score Calibration in Face Recognition".
Home-page: http://gitlab.idiap.ch/manuel.guenther/xfacereclib-paper-iet2014
Author: Manuel Guenther
Author-email: manuel.guenther@idiap.ch
License: LICENSE.txt
Platform: UNKNOWN
Classifier: Development Status :: 4 - Beta
Classifier: Intended Audience :: Science/Research
Classifier: License :: OSI Approved :: GNU General Public License v3 (GPLv3)
Classifier: Natural Language :: English
Classifier: Programming Language :: Python :: 2.7
Classifier: Environment :: Console
Classifier: Framework :: Buildout
Classifier: Topic :: Scientific/Engineering
